sqruff-0.32.0.dist-info/METADATA
sqruff-0.32.0.dist-info/WHEEL
sqruff-0.32.0.dist-info/entry_points.txt
sqruff/__init__.py
sqruff/_lib_name.cpython-313t-darwin.so
sqruff/main.py
sqruff/templaters/__init__.py
sqruff/templaters/dbt_templater.py
sqruff/templaters/dbt_templater_test.py
sqruff/templaters/jinja_templater.py
sqruff/templaters/jinja_templater_builtins_common.py
sqruff/templaters/jinja_templater_builtins_dbt.py
sqruff/templaters/jinja_templater_test.py
sqruff/templaters/jinja_templater_tracers.py
sqruff/templaters/python_templater.py
sqruff/templaters/python_templater_test.py
sqruff-0.32.0.dist-info/RECORD
