Metadata-Version: 2.4
Name: sqruff
Version: 0.32.0
Requires-Dist: regex ; extra == 'jinja'
Requires-Dist: jinja2>=3.0.0 ; extra == 'jinja'
Requires-Dist: jinja2-simple-tags>=0.3.1 ; extra == 'jinja'
Requires-Dist: regex ; extra == 'dbt'
Requires-Dist: jinja2>=3.0.0 ; extra == 'dbt'
Requires-Dist: jinja2-simple-tags>=0.3.1 ; extra == 'dbt'
Requires-Dist: dbt-core>=1.4.1 ; extra == 'dbt'
Provides-Extra: jinja
Provides-Extra: dbt
Summary: A SQL linter written in rust.
Requires-Python: >=3.9
